{
    "category": "COAG", 
    "edit_all_groups": [], 
    "source_url_text": "ABS Survey of Income and Housing", 
    "subtitle": "", 
    "subcategory": "housing", 
    "groups": [], 
    "url": "rental_stress", 
    "definitions": [
        {
            "tiles": [
                {
                    "expansion": false, 
                    "sort_order": 5, 
                    "aspect": 0, 
                    "statistics": [
                        {
                            "num_precision": 1, 
                            "icon_library": null, 
                            "name": "", 
                            "numbered_list": false, 
                            "hyperlinkable": false, 
                            "url": "outcome", 
                            "traffic_light_automation": null, 
                            "footer": false, 
                            "editable": true, 
                            "name_as_label": true, 
                            "trend": true, 
                            "traffic_light_scale": "Benchmark Scale", 
                            "unit_underfix": "", 
                            "unit_signed": false, 
                            "unit_si_prefix_rounding": 0, 
                            "unit_suffix": "%", 
                            "rotates": false, 
                            "stat_type": 2, 
                            "unit_prefix": "", 
                            "sort_order": 100
                        }, 
                        {
                            "num_precision": null, 
                            "icon_library": null, 
                            "name": "", 
                            "numbered_list": false, 
                            "hyperlinkable": false, 
                            "url": "outcome_type", 
                            "traffic_light_automation": null, 
                            "footer": false, 
                            "editable": true, 
                            "name_as_label": true, 
                            "trend": false, 
                            "traffic_light_scale": null, 
                            "unit_underfix": null, 
                            "unit_signed": false, 
                            "unit_si_prefix_rounding": 0, 
                            "unit_suffix": null, 
                            "rotates": false, 
                            "stat_type": 1, 
                            "unit_prefix": null, 
                            "sort_order": 200
                        }
                    ], 
                    "list_label_width": null, 
                    "url": "rental_stress_outcome", 
                    "tile_type": 1, 
                    "geo_datasets": [], 
                    "geo_window": null, 
                    "template": null, 
                    "columns": null
                }, 
                {
                    "expansion": false, 
                    "sort_order": 10, 
                    "aspect": 0, 
                    "statistics": [
                        {
                            "num_precision": 1, 
                            "icon_library": null, 
                            "name": "Benchmark", 
                            "numbered_list": false, 
                            "hyperlinkable": false, 
                            "url": "benchmark", 
                            "traffic_light_automation": null, 
                            "footer": false, 
                            "editable": true, 
                            "name_as_label": true, 
                            "trend": true, 
                            "traffic_light_scale": null, 
                            "unit_underfix": "", 
                            "unit_signed": false, 
                            "unit_si_prefix_rounding": 0, 
                            "unit_suffix": "%", 
                            "rotates": false, 
                            "stat_type": 2, 
                            "unit_prefix": "", 
                            "sort_order": 100
                        }, 
                        {
                            "num_precision": null, 
                            "icon_library": null, 
                            "name": "by", 
                            "numbered_list": false, 
                            "hyperlinkable": false, 
                            "url": "benchmark_year", 
                            "traffic_light_automation": null, 
                            "footer": false, 
                            "editable": true, 
                            "name_as_label": true, 
                            "trend": false, 
                            "traffic_light_scale": null, 
                            "unit_underfix": null, 
                            "unit_signed": false, 
                            "unit_si_prefix_rounding": 0, 
                            "unit_suffix": null, 
                            "rotates": false, 
                            "stat_type": 1, 
                            "unit_prefix": null, 
                            "sort_order": 200
                        }
                    ], 
                    "list_label_width": null, 
                    "url": "rental_stress_benchmark", 
                    "tile_type": 1, 
                    "geo_datasets": [], 
                    "geo_window": null, 
                    "template": null, 
                    "columns": null
                }, 
                {
                    "expansion": false, 
                    "sort_order": 20, 
                    "aspect": 0, 
                    "statistics": [
                        {
                            "num_precision": 1, 
                            "icon_library": null, 
                            "name": "", 
                            "numbered_list": false, 
                            "hyperlinkable": false, 
                            "url": "data", 
                            "traffic_light_automation": null, 
                            "footer": false, 
                            "editable": true, 
                            "name_as_label": true, 
                            "trend": false, 
                            "traffic_light_scale": null, 
                            "unit_underfix": "", 
                            "unit_signed": false, 
                            "unit_si_prefix_rounding": 0, 
                            "unit_suffix": "%", 
                            "rotates": false, 
                            "stat_type": 4, 
                            "unit_prefix": "", 
                            "sort_order": 111
                        }
                    ], 
                    "list_label_width": 30, 
                    "url": "rental_stress_stats", 
                    "tile_type": 10, 
                    "geo_datasets": [], 
                    "geo_window": null, 
                    "template": null, 
                    "columns": 1
                }
            ], 
            "views": [
                {
                    "sort_order": 100, 
                    "view": "housing"
                }
            ], 
            "default_frequency_text": "Annual", 
            "raw_data_sets": [
                {
                    "url": "rental_stress_data", 
                    "name": "Rental Stress Data", 
                    "columns": [
                        {
                            "url": "jurisdiction", 
                            "sort_order": 100, 
                            "heading": "Jurisdiction", 
                            "description": "The Jurisdiction each row describes: A state or territory, or all of Australia."
                        }, 
                        {
                            "url": "year", 
                            "sort_order": 200, 
                            "heading": "Year", 
                            "description": "The calendar or financial year each row describes."
                        }, 
                        {
                            "url": "percentage_rental_stress", 
                            "sort_order": 300, 
                            "heading": "Proportion of households in rental stress (%)", 
                            "description": "The proportion of low income households in rental stress (%)."
                        }, 
                        {
                            "url": "uncertainty", 
                            "sort_order": 400, 
                            "heading": "Uncertainty", 
                            "description": "The uncertainty in the main percentage of households in rental stress figure."
                        }
                    ], 
                    "filename": "coag_rental_stress_data.csv"
                }
            ], 
            "sort_order": 100, 
            "expansion_hint": "View details", 
            "about": "<ol>\r\n<li>A household is deemed to be experiencing rental stress if more than 30 per cent of their gross income goes towards rental costs.</li>\r\n<li>A household is classified as \u2018low income\u2019 if household income is in the bottom 40 per cent of incomes, calculated for capital city and balance of\r\nstate, on a state\u2010by\u2010state basis.</li>\r\n<li>Commonwealth Rent Assistance is excluded from both gross income and housing costs.</li>\r\n<li>Excludes households in collection districts defined as very remote, accounting for about 25 per cent of the population in the NT.</li>\r\n</ol>\r\n<p><b>Source:</b> ABS (unpublished) <i>Survey of Income and Housing</i></p>", 
            "refresh_rate": 120, 
            "label": "rental_stress", 
            "parametisation": null, 
            "deexpansion_hint": "Hide details"
        }
    ], 
    "source_url": "http://www.abs.gov.au/ausstats/abs@.nsf/dossbytitle/F0CDB39ECC092711CA256BD00026C3D5?OpenDocument", 
    "name": "Low-income renter households in renter stress"
}

